setup.py
l1tool/__init__.py
l1tool/app.py
l1tool/l1tool.py
l1tool/reader.py
l1tool.egg-info/PKG-INFO
l1tool.egg-info/SOURCES.txt
l1tool.egg-info/dependency_links.txt
l1tool.egg-info/entry_points.txt
l1tool.egg-info/requires.txt
l1tool.egg-info/top_level.txt