Metadata-Version: 1.0
Name: l1tool
Version: 1.0.1
Summary: L1 Regularizer for GNSS Time series change and offsets detection.
Home-page: https://github.com/wudingcheng/l1tool
Author: WU Dingcheng
Author-email: UNKNOWN
License: GPL v3
Platform: UNKNOWN
